Workbook
Name Semester: "2024 Spring"

Sheet Q1 Actual
A1: Jan - Mar Sales Summary - Actual
B2: Model | C2: Sales Volume | D2: % of total Volume | E2: Mfg. Cost per Vehicle | F2: Selling Price to Dealer | G2: Gross Profit Margin: Hint:1-Cost/Sell | H2: Total Cost: Hint: Cost * Volume | I2: Total Sales to Dealers: Hint: Volume*Sell
B3: 500X Turtleneck | C3: 8691 | D3: =C3/C$25 -> 0.056791672 | E3: 28860 | F3: 31450 | G3: =1-E3/F3 -> 0.082352941 | H3: =E3*C3 -> 250822260 | I3: =F3*C3 -> 273331950
B4: 500X Dolce Vita | C4: 7586 | D4: =C4/C$25 -> 0.049571008 | E4: 29716 | F4: 32150 | G4: =1-E4/F4 -> 0.075707621 | H4: =E4*C4 -> 225425576 | I4: =F4*C4 -> 243889900
B5: 500 Hybrid | C5: 7439 | D5: =C5/C$25 -> 0.04861043 | E5: 17738 | F5: 19119 | G5: =1-E5/F5 -> 0.072231811 | H5: =E5*C5 -> 131952982 | I5: =F5*C5 -> 142226241
B6: 501 Hybrid Convertible | C6: 0 | D6: =C6/C$25 -> 0 | E6: 19356 | F6: 20900 | G6: =1-E6/F6 -> 0.073875598 | H6: =E6*C6 -> 0 | I6: =F6*C6 -> 0
B7: 500 Electric | C7: 9958 | D7: =C7/C$25 -> 0.065070932 | E7: 26263 | F7: 28450 | G7: =1-E7/F7 -> 0.076871705 | H7: =E7*C7 -> 261526954 | I7: =F7*C7 -> 283305100
B8: 500 Electric Cabriolet | C8: 5865 | D8: =C8/C$25 -> 0.038325067 | E8: 27847 | F8: 30175 | G8: =1-E8/F8 -> 0.077149959 | H8: =E8*C8 -> 163322655 | I8: =F8*C8 -> 176976375
B9: 500 Electric 3+1 | C9: 8706 | D9: =C9/C$25 -> 0.05688969 | E9: 30025 | F9: 32350 | G9: =1-E9/F9 -> 0.07187017 | H9: =E9*C9 -> 261397650 | I9: =F9*C9 -> 281639100
B10: Doblo Electric | C10: 0 | D10: =C10/C$25 -> 0 | E10: 35096 | F10: 38200 | G10: =1-E10/F10 -> 0.081256545 | H10: =E10*C10 -> 0 | I10: =F10*C10 -> 0
B11: Doblo Electric Magic Top | C11: 10023 | D11: =C11/C$25 -> 0.065495677 | E11: 38762 | F11: 42500 | G11: =1-E11/F11 -> 0.087952941 | H11: =E11*C11 -> 388511526 | I11: =F11*C11 -> 425977500
B12: Doblo Electric Launch | C12: 9054 | D12: =C12/C$25 -> 0.05916371 | E12: 37154 | F12: 40400 | G12: =1-E12/F12 -> 0.080346535 | H12: =E12*C12 -> 336392316 | I12: =F12*C12 -> 365781600
B13: Ulysse Electric | C13: 7705 | D13: =C13/C$25 -> 0.050348618 | E13: 59967 | F13: 64900 | G13: =1-E13/F13 -> 0.076009245 | H13: =E13*C13 -> 462045735 | I13: =F13*C13 -> 500054500
B14: Ulysse Electric Living | C14: 5938 | D14: =C14/C$25 -> 0.038802088 | E14: 57536 | F14: 62350 | G14: =1-E14/F14 -> 0.077209302 | H14: =E14*C14 -> 341648768 | I14: =F14*C14 -> 370234300
... B23: Tipo Station Wagon | C23: 10498 | D23: =C23/C$25 -> 0.068599583 | E23: 28206 | F23: 30900 | G23: =1-E23/F23 -> 0.087184466 | H23: =E23*C23 -> 296106588 | I23: =F23*C23 -> 324388200
B25: 2024 Spring | C25: =SUM(C3:C23) -> 153033 | H25: =SUM(H3:H23) -> 4744885753 | I25: =SUM(I3:I23) -> 5.1565276e+09
B26: Average | C26: =AVERAGE(C3:C23) -> 7287.2857 | E26: =AVERAGE(E3:E23) -> 30960.238 | F26: =AVERAGE(F3:F23) -> 33627.979 | H26: =AVERAGE(H3:H23) -> 2.2594694e+08 | I26: =AVERAGE(I3:I23) -> 2.4554893e+08
B27: Highest | C27: =MAX(C3:C23) -> 10498
B28: Lowest | C28: =MIN(C3:C23) -> 0
B30: # of models available for sale (regardless of whether or not there were sales for that model) | G30: =COUNTA(B3:B23) -> 21
B32: 45286
B37: =Semester -> 2024 Spring

Sheet Q2
A1: April - June Sales Summary - Estimate
B2: Model | C2: Sales Volume | D2: % of total Volume | E2: Mfg. Cost per Vehicle | F2: Selling Price to Dealer | G2: Gross Profit Margin: Hint:1-Cost/Sell | H2: Total Cost: Hint: Cost * Volume | I2: Total Sales to Dealers: Hint: Volume*Sell
B3: 500X Turtleneck | C3: 7670 | D3: =C3/C$25 -> 0.042550123 | E3: 28860 | F3: 31450 | G3: =1-E3/F3 -> 0.082352941 | H3: =E3*C3 -> 221356200 | I3: =F3*C3 -> 241221500
B4: 500X Dolce Vita | C4: 10576 | D4: =C4/C$25 -> 0.05867146 | E4: 29716 | F4: 32150 | G4: =1-E4/F4 -> 0.075707621 | H4: =E4*C4 -> 314276416 | I4: =F4*C4 -> 340018400
B5: 500 Hybrid | C5: 7315 | D5: =C5/C$25 -> 0.040580723 | E5: 17738 | F5: 19119 | G5: =1-E5/F5 -> 0.072231811 | H5: =E5*C5 -> 129753470 | I5: =F5*C5 -> 139855485
B6: 501 Hybrid Convertible | C6: 9145 | D6: =C6/C$25 -> 0.050732838 | E6: 19356 | F6: 20900 | G6: =1-E6/F6 -> 0.073875598 | H6: =E6*C6 -> 177010620 | I6: =F6*C6 -> 191130500
B7: 500 Electric | C7: 7938 | D7: =C7/C$25 -> 0.04403688 | E7: 26263 | F7: 28450 | G7: =1-E7/F7 -> 0.076871705 | H7: =E7*C7 -> 208475694 | I7: =F7*C7 -> 225836100
B8: 500 Electric Cabriolet | C8: 10074 | D8: =C8/C$25 -> 0.055886563 | E8: 27847 | F8: 30175 | G8: =1-E8/F8 -> 0.077149959 | H8: =E8*C8 -> 280530678 | I8: =F8*C8 -> 303982950
B9: 500 Electric 3+1 | C9: 10571 | D9: =C9/C$25 -> 0.058643722 | E9: 30025 | F9: 32350 | G9: =1-E9/F9 -> 0.07187017 | H9: =E9*C9 -> 317394275 | I9: =F9*C9 -> 341971850
B10: Doblo Electric | C10: 9064 | D10: =C10/C$25 -> 0.050283483 | E10: 35096 | F10: 38200 | G10: =1-E10/F10 -> 0.081256545 | H10: =E10*C10 -> 318110144 | I10: =F10*C10 -> 346244800
B11: Doblo Electric Magic Top | C11: 8130 | D11: =C11/C$25 -> 0.04510202 | E11: 38762 | F11: 42500 | G11: =1-E11/F11 -> 0.087952941 | H11: =E11*C11 -> 315135060 | I11: =F11*C11 -> 345525000
B12: Doblo Electric Launch | C12: 10086 | D12: =C12/C$25 -> 0.055953134 | E12: 37154 | F12: 40400 | G12: =1-E12/F12 -> 0.080346535 | H12: =E12*C12 -> 374735244 | I12: =F12*C12 -> 407474400
B13: Ulysse Electric | C13: 7649 | D13: =C13/C$25 -> 0.042433623 | E13: 59967 | F13: 64900 | G13: =1-E13/F13 -> 0.076009245 | H13: =E13*C13 -> 458687583 | I13: =F13*C13 -> 496420100
B14: Ulysse Electric Living | C14: 10481 | D14: =C14/C$25 -> 0.058144437 | E14: 57536 | F14: 62350 | G14: =1-E14/F14 -> 0.077209302 | H14: =E14*C14 -> 603034816 | I14: =F14*C14 -> 653490350
... B23: Tipo Station Wagon | C23: 10839 | D23: =C23/C$25 -> 0.06013048 | E23: 28206 | F23: 30900 | G23: =1-E23/F23 -> 0.087184466 | H23: =E23*C23 -> 305724834 | I23: =F23*C23 -> 334925100
B25: 2024 Spring | C25: =SUM(C3:C23) -> 180258 | H25: =SUM(H3:H23) -> 5612257816 | I25: =SUM(I3:I23) -> 6.0942858e+09
B26: Average | C26: =AVERAGE(C3:C23) -> 8583.7143 | E26: =AVERAGE(E3:E23) -> 30960.238 | F26: =AVERAGE(F3:F23) -> 33627.979 | H26: =AVERAGE(H3:H23) -> 2.6725037e+08 | I26: =AVERAGE(I3:I23) -> 2.9020409e+08
B27: Highest | C27: =MAX(C3:C23) -> 11188
B28: Lowest | C28: =MIN(C3:C23) -> 0
B30: # of models available for sale (regardless of whether or not there were sales for that model) | G30: =COUNTA(B3:B23) -> 21
B32: 45286
B37: =Semester -> 2024 Spring

Sheet Q3
A1: July-September Sales Summary - Estimate
B2: Model | C2: Sales Volume | D2: % of total Volume | E2: Mfg. Cost per Vehicle | F2: Selling Price to Dealer | G2: Gross Profit Margin: Hint:1-Cost/Sell | H2: Total Cost: Hint: Cost * Volume | I2: Total Sales to Dealers: Hint: Volume*Sell
B3: 500X Turtleneck | C3: 7174 | D3: =C3/C$25 -> 0.040071273 | E3: 28860 | F3: 31450 | G3: =1-E3/F3 -> 0.082352941 | H3: =E3*C3 -> 207041640 | I3: =F3*C3 -> 225622300
B4: 500X Dolce Vita | C4: 10407 | D4: =C4/C$25 -> 0.058129598 | E4: 29716 | F4: 32150 | G4: =1-E4/F4 -> 0.075707621 | H4: =E4*C4 -> 309254412 | I4: =F4*C4 -> 334585050
B5: 500 Hybrid | C5: 8882 | D5: =C5/C$25 -> 0.04961152 | E5: 17738 | F5: 19119 | G5: =1-E5/F5 -> 0.072231811 | H5: =E5*C5 -> 157548916 | I5: =F5*C5 -> 169814958
B6: 501 Hybrid Convertible | C6: 9167 | D6: =C6/C$25 -> 0.051203423 | E6: 19356 | F6: 20900 | G6: =1-E6/F6 -> 0.073875598 | H6: =E6*C6 -> 177436452 | I6: =F6*C6 -> 191590300
B7: 500 Electric | C7: 9427 | D7: =C7/C$25 -> 0.052655685 | E7: 26263 | F7: 28450 | G7: =1-E7/F7 -> 0.076871705 | H7: =E7*C7 -> 247581301 | I7: =F7*C7 -> 268198150
B8: 500 Electric Cabriolet | C8: 9134 | D8: =C8/C$25 -> 0.051019097 | E8: 27847 | F8: 30175 | G8: =1-E8/F8 -> 0.077149959 | H8: =E8*C8 -> 254354498 | I8: =F8*C8 -> 275618450
B9: 500 Electric 3+1 | C9: 10254 | D9: =C9/C$25 -> 0.057274997 | E9: 30025 | F9: 32350 | G9: =1-E9/F9 -> 0.07187017 | H9: =E9*C9 -> 307876350 | I9: =F9*C9 -> 331716900
B10: Doblo Electric | C10: 10944 | D10: =C10/C$25 -> 0.061129078 | E10: 35096 | F10: 38200 | G10: =1-E10/F10 -> 0.081256545 | H10: =E10*C10 -> 384090624 | I10: =F10*C10 -> 418060800
B11: Doblo Electric Magic Top | C11: 10760 | D11: =C11/C$25 -> 0.060101323 | E11: 38762 | F11: 42500 | G11: =1-E11/F11 -> 0.087952941 | H11: =E11*C11 -> 417079120 | I11: =F11*C11 -> 457300000
B12: Doblo Electric Launch | C12: 8375 | D12: =C12/C$25 -> 0.046779608 | E12: 37154 | F12: 40400 | G12: =1-E12/F12 -> 0.080346535 | H12: =E12*C12 -> 311164750 | I12: =F12*C12 -> 338350000
B13: Ulysse Electric | C13: 7740 | D13: =C13/C$25 -> 0.043232736 | E13: 59967 | F13: 64900 | G13: =1-E13/F13 -> 0.076009245 | H13: =E13*C13 -> 464144580 | I13: =F13*C13 -> 502326000
B14: Ulysse Electric Living | C14: 9108 | D14: =C14/C$25 -> 0.050873871 | E14: 57536 | F14: 62350 | G14: =1-E14/F14 -> 0.077209302 | H14: =E14*C14 -> 524037888 | I14: =F14*C14 -> 567883800
... B23: Tipo Station Wagon | C23: 7494 | D23: =C23/C$25 -> 0.041858673 | E23: 28206 | F23: 30900 | G23: =1-E23/F23 -> 0.087184466 | H23: =E23*C23 -> 211375764 | I23: =F23*C23 -> 231564600
B25: 2024 Spring | C25: =SUM(C3:C23) -> 179031 | H25: =SUM(H3:H23) -> 5636143951 | I25: =SUM(I3:I23) -> 6.1208002e+09
B26: Average | C26: =AVERAGE(C3:C23) -> 8525.2857 | E26: =AVERAGE(E3:E23) -> 30960.238 | F26: =AVERAGE(F3:F23) -> 33627.979 | H26: =AVERAGE(H3:H23) -> 2.6838781e+08 | I26: =AVERAGE(I3:I23) -> 2.9146668e+08
B27: Highest | C27: =MAX(C3:C23) -> 10944
B28: Lowest | C28: =MIN(C3:C23) -> 0
B30: # of models available for sale (regardless of whether or not there were sales for that model) | G30: =COUNTA(B3:B23) -> 21
B32: 45286
B37: =Semester -> 2024 Spring

Sheet Q4
A1: October-December Sales Summary - Estimate
B2: Model | C2: Sales Volume | D2: % of total Volume | E2: Mfg. Cost per Vehicle | F2: Selling Price to Dealer | G2: Gross Profit Margin: Hint:1-Cost/Sell | H2: Total Cost: Hint: Cost * Volume | I2: Total Sales to Dealers: Hint: Volume*Sell
B3: 500X Turtleneck | C3: 9931 | D3: =C3/C$25 -> 0.054251751 | E3: 28860 | F3: 31450 | G3: =1-E3/F3 -> 0.082352941 | H3: =E3*C3 -> 286608660 | I3: =F3*C3 -> 312329950
B4: 500X Dolce Vita | C4: 10036 | D4: =C4/C$25 -> 0.054825352 | E4: 29716 | F4: 32150 | G4: =1-E4/F4 -> 0.075707621 | H4: =E4*C4 -> 298229776 | I4: =F4*C4 -> 322657400
B5: 500 Hybrid | C5: 7588 | D5: =C5/C$25 -> 0.041452249 | E5: 17738 | F5: 19119 | G5: =1-E5/F5 -> 0.072231811 | H5: =E5*C5 -> 134595944 | I5: =F5*C5 -> 145074972
B6: 501 Hybrid Convertible | C6: 7299 | D6: =C6/C$25 -> 0.03987348 | E6: 19356 | F6: 20900 | G6: =1-E6/F6 -> 0.073875598 | H6: =E6*C6 -> 141279444 | I6: =F6*C6 -> 152549100
B7: 500 Electric | C7: 9806 | D7: =C7/C$25 -> 0.053568892 | E7: 26263 | F7: 28450 | G7: =1-E7/F7 -> 0.076871705 | H7: =E7*C7 -> 257534978 | I7: =F7*C7 -> 278980700
B8: 500 Electric Cabriolet | C8: 10832 | D8: =C8/C$25 -> 0.059173796 | E8: 27847 | F8: 30175 | G8: =1-E8/F8 -> 0.077149959 | H8: =E8*C8 -> 301638704 | I8: =F8*C8 -> 326855600
B9: 500 Electric 3+1 | C9: 9749 | D9: =C9/C$25 -> 0.053257509 | E9: 30025 | F9: 32350 | G9: =1-E9/F9 -> 0.07187017 | H9: =E9*C9 -> 292713725 | I9: =F9*C9 -> 315380150
B10: Doblo Electric | C10: 9077 | D10: =C10/C$25 -> 0.049586461 | E10: 35096 | F10: 38200 | G10: =1-E10/F10 -> 0.081256545 | H10: =E10*C10 -> 318566392 | I10: =F10*C10 -> 346741400
B11: Doblo Electric Magic Top | C11: 7685 | D11: =C11/C$25 -> 0.041982147 | E11: 38762 | F11: 42500 | G11: =1-E11/F11 -> 0.087952941 | H11: =E11*C11 -> 297885970 | I11: =F11*C11 -> 326612500
B12: Doblo Electric Launch | C12: 10592 | D12: =C12/C$25 -> 0.057862707 | E12: 37154 | F12: 40400 | G12: =1-E12/F12 -> 0.080346535 | H12: =E12*C12 -> 393535168 | I12: =F12*C12 -> 427916800
B13: Ulysse Electric | C13: 10179 | D13: =C13/C$25 -> 0.055606542 | E13: 59967 | F13: 64900 | G13: =1-E13/F13 -> 0.076009245 | H13: =E13*C13 -> 610404093 | I13: =F13*C13 -> 660617100
B14: Ulysse Electric Living | C14: 6689 | D14: =C14/C$25 -> 0.03654113 | E14: 57536 | F14: 62350 | G14: =1-E14/F14 -> 0.077209302 | H14: =E14*C14 -> 384858304 | I14: =F14*C14 -> 417059150
... B23: Tipo Station Wagon | C23: 7504 | D23: =C23/C$25 -> 0.040993368 | E23: 28206 | F23: 30900 | G23: =1-E23/F23 -> 0.087184466 | H23: =E23*C23 -> 211657824 | I23: =F23*C23 -> 231873600
B25: 2024 Spring | C25: =SUM(C3:C23) -> 183054 | H25: =SUM(H3:H23) -> 5672744467 | I25: =SUM(I3:I23) -> 6.1596954e+09
B26: Average | C26: =AVERAGE(C3:C23) -> 8716.8571 | E26: =AVERAGE(E3:E23) -> 30960.238 | F26: =AVERAGE(F3:F23) -> 33627.979 | H26: =AVERAGE(H3:H23) -> 2.7013069e+08 | I26: =AVERAGE(I3:I23) -> 2.9331883e+08
B27: Highest | C27: =MAX(C3:C23) -> 10832
B28: Lowest | C28: =MIN(C3:C23) -> 6677
B30: # of models available for sale (regardless of whether or not there were sales for that model) | G30: =COUNTA(B3:B23) -> 21
B32: 45286
B37: =Semester -> 2024 Spring

Sheet Summary
A1: Yearly Sales Summary - Estimated
A2: Model | B2: Annual Volume | C2: Q1(Jan-Mar) Sales to Dealers | D2: Q2(Apr-Jun) Sales to Dealers | E2: Q3(Jul-Sep) Sales to Dealers | F2: Q4(Oct-Dec) Sales to Dealers | G2: Total Sales to Dealers | H2: Model's Q1 Contribution to Total Sales% | I2: Model's Q2 Contribution to Total Sales% | J2: Model's Q3 Contribution to Total Sales% | K2: Model's Q4 Contribution to Total Sales% | L2: Model's Annual Contribution to Total Sales%
A3: 500X Turtleneck | B3: =SUM('Q1 Actual:Q4'!$C3) -> 33466 | C3: ='Q1 Actual'!$I3 -> 273331950 | D3: ='Q2'!$I3 -> 241221500 | E3: ='Q3'!$I3 -> 225622300 | F3: ='Q4'!$I3 -> 312329950 | G3: =SUM($C3:$F3) -> 1052505700 | H3: =C3/$G$25 -> 0.011615671 | I3: =D3/$G$25 -> 0.010251087 | J3: =E3/$G$25 -> 0.0095881746 | K3: =F3/$G$25 -> 0.013272953 | L3: =G3/$G$25 -> 0.044727886
A4: 500X Dolce Vita | B4: =SUM('Q1 Actual:Q4'!$C4) -> 38605 | C4: ='Q1 Actual'!$I4 -> 243889900 | D4: ='Q2'!$I4 -> 340018400 | E4: ='Q3'!$I4 -> 334585050 | F4: ='Q4'!$I4 -> 322657400 | G4: =SUM($C4:$F4) -> 1241150750 | H4: =C4/$G$25 -> 0.010364485 | I4: =D4/$G$25 -> 0.014449617 | J4: =E4/$G$25 -> 0.014218718 | K4: =F4/$G$25 -> 0.013711834 | L4: =G4/$G$25 -> 0.052744654
A5: 500 Hybrid | B5: =SUM('Q1 Actual:Q4'!$C5) -> 31224 | C5: ='Q1 Actual'!$I5 -> 142226241 | D5: ='Q2'!$I5 -> 139855485 | E5: ='Q3'!$I5 -> 169814958 | F5: ='Q4'!$I5 -> 145074972 | G5: =SUM($C5:$F5) -> 596971656 | H5: =C5/$G$25 -> 0.0060441279 | I5: =D5/$G$25 -> 0.0059433789 | J5: =E5/$G$25 -> 0.0072165538 | K5: =F5/$G$25 -> 0.0061651892 | L5: =G5/$G$25 -> 0.02536925
A6: 501 Hybrid Convertible | B6: =SUM('Q1 Actual:Q4'!$C6) -> 25611 | C6: ='Q1 Actual'!$I6 -> 0 | D6: ='Q2'!$I6 -> 191130500 | E6: ='Q3'!$I6 -> 191590300 | F6: ='Q4'!$I6 -> 152549100 | G6: =SUM($C6:$F6) -> 535269900 | H6: =C6/$G$25 -> 0 | I6: =D6/$G$25 -> 0.0081223913 | J6: =E6/$G$25 -> 0.0081419313 | K6: =F6/$G$25 -> 0.006482814 | L6: =G6/$G$25 -> 0.022747137
A7: 500 Electric | B7: =SUM('Q1 Actual:Q4'!$C7) -> 37129 | C7: ='Q1 Actual'!$I7 -> 283305100 | D7: ='Q2'!$I7 -> 225836100 | E7: ='Q3'!$I7 -> 268198150 | F7: ='Q4'!$I7 -> 278980700 | G7: =SUM($C7:$F7) -> 1056320050 | H7: =C7/$G$25 -> 0.012039496 | I7: =D7/$G$25 -> 0.0095972604 | J7: =E7/$G$25 -> 0.011397502 | K7: =F7/$G$25 -> 0.011855724 | L7: =G7/$G$25 -> 0.044889983
A8: 500 Electric Cabriolet | B8: =SUM('Q1 Actual:Q4'!$C8) -> 35905 | C8: ='Q1 Actual'!$I8 -> 176976375 | D8: ='Q2'!$I8 -> 303982950 | E8: ='Q3'!$I8 -> 275618450 | F8: ='Q4'!$I8 -> 326855600 | G8: =SUM($C8:$F8) -> 1083433375 | H8: =C8/$G$25 -> 0.0075208895 | I8: =D8/$G$25 -> 0.012918234 | J8: =E8/$G$25 -> 0.01171284 | K8: =F8/$G$25 -> 0.013890243 | L8: =G8/$G$25 -> 0.046042206
A9: 500 Electric 3+1 | B9: =SUM('Q1 Actual:Q4'!$C9) -> 39280 | C9: ='Q1 Actual'!$I9 -> 281639100 | D9: ='Q2'!$I9 -> 341971850 | E9: ='Q3'!$I9 -> 331716900 | F9: ='Q4'!$I9 -> 315380150 | G9: =SUM($C9:$F9) -> 1270708000 | H9: =C9/$G$25 -> 0.011968697 | I9: =D9/$G$25 -> 0.014532632 | J9: =E9/$G$25 -> 0.014096832 | K9: =F9/$G$25 -> 0.013402576 | L9: =G9/$G$25 -> 0.054000736
A10: Doblo Electric | B10: =SUM('Q1 Actual:Q4'!$C10) -> 29085 | C10: ='Q1 Actual'!$I10 -> 0 | D10: ='Q2'!$I10 -> 346244800 | E10: ='Q3'!$I10 -> 418060800 | F10: ='Q4'!$I10 -> 346741400 | G10: =SUM($C10:$F10) -> 1111047000 | H10: =C10/$G$25 -> 0 | I10: =D10/$G$25 -> 0.014714218 | J10: =E10/$G$25 -> 0.017766151 | K10: =F10/$G$25 -> 0.014735321 | L10: =G10/$G$25 -> 0.04721569
A11: Doblo Electric Magic Top | B11: =SUM('Q1 Actual:Q4'!$C11) -> 36598 | C11: ='Q1 Actual'!$I11 -> 425977500 | D11: ='Q2'!$I11 -> 345525000 | E11: ='Q3'!$I11 -> 457300000 | F11: ='Q4'!$I11 -> 326612500 | G11: =SUM($C11:$F11) -> 1555415000 | H11: =C11/$G$25 -> 0.018102584 | I11: =D11/$G$25 -> 0.014683629 | J11: =E11/$G$25 -> 0.019433683 | K11: =F11/$G$25 -> 0.013879912 | L11: =G11/$G$25 -> 0.066099808
A12: Doblo Electric Launch | B12: =SUM('Q1 Actual:Q4'!$C12) -> 38107 | C12: ='Q1 Actual'!$I12 -> 365781600 | D12: ='Q2'!$I12 -> 407474400 | E12: ='Q3'!$I12 -> 338350000 | F12: ='Q4'!$I12 -> 427916800 | G12: =SUM($C12:$F12) -> 1539522800 | H12: =C12/$G$25 -> 0.015544465 | I12: =D12/$G$25 -> 0.017316266 | J12: =E12/$G$25 -> 0.014378716 | K12: =F12/$G$25 -> 0.018184998 | L12: =G12/$G$25 -> 0.065424444
A13: Ulysse Electric | B13: =SUM('Q1 Actual:Q4'!$C13) -> 33273 | C13: ='Q1 Actual'!$I13 -> 500054500 | D13: ='Q2'!$I13 -> 496420100 | E13: ='Q3'!$I13 -> 502326000 | F13: ='Q4'!$I13 -> 660617100 | G13: =SUM($C13:$F13) -> 2159417700 | H13: =C13/$G$25 -> 0.021250603 | I13: =D13/$G$25 -> 0.021096153 | J13: =E13/$G$25 -> 0.021347134 | K13: =F13/$G$25 -> 0.028073963 | L13: =G13/$G$25 -> 0.091767853
A14: Ulysse Electric Living | B14: =SUM('Q1 Actual:Q4'!$C14) -> 32216 | C14: ='Q1 Actual'!$I14 -> 370234300 | D14: ='Q2'!$I14 -> 653490350 | E14: ='Q3'!$I14 -> 567883800 | F14: ='Q4'!$I14 -> 417059150 | G14: =SUM($C14:$F14) -> 2008667600 | H14: =C14/$G$25 -> 0.015733689 | I14: =D14/$G$25 -> 0.027771101 | J14: =E14/$G$25 -> 0.024133116 | K14: =F14/$G$25 -> 0.017723585 | L14: =G14/$G$25 -> 0.08536149
... A23: Tipo Station Wagon | B23: =SUM('Q1 Actual:Q4'!$C23) -> 36335 | C23: ='Q1 Actual'!$I23 -> 324388200 | D23: ='Q2'!$I23 -> 334925100 | E23: ='Q3'!$I23 -> 231564600 | F23: ='Q4'!$I23 -> 231873600 | G23: =SUM($C23:$F23) -> 1122751500 | H23: =C23/$G$25 -> 0.013785387 | I23: =D23/$G$25 -> 0.014233169 | J23: =E23/$G$25 -> 0.009840702 | K23: =F23/$G$25 -> 0.0098538335 | L23: =G23/$G$25 -> 0.047713092
A25: Totals | B25: =SUM(B3:B23) -> 695376 | C25: =SUM(C3:C23) -> 5.1565276e+09 | D25: =SUM(D3:D23) -> 6.0942858e+09 | E25: =SUM(E3:E23) -> 6.1208002e+09 | F25: =SUM(F3:F23) -> 6.1596954e+09 | G25: =SUM(G3:G23) -> 2.3531309e+10
